afs/__init__.py
afs/get_env.py
afs/models.py
afs/utils.py
tests/v2/__init__.py
tests/v2/conftest.py
tests/v2/test_model_repo.py
tests/v2/test_models.py
tests/v2/test_models_api.py
tests/v2/test_models_dev.py
tests/v2/test_models_token.py
afs2_model-3.8.2.dist-info/LICENSE
afs2_model-3.8.2.dist-info/METADATA
afs2_model-3.8.2.dist-info/WHEEL
afs2_model-3.8.2.dist-info/entry_points.txt
afs2_model-3.8.2.dist-info/top_level.txt
afs2_model-3.8.2.dist-info/RECORD
