Metadata-Version: 2.1
Name: afs2-model
Version: 3.8.2
Summary: For AFS developer to develop analytics
Home-page: https://github.com/benchuang11046/afs2-model
Author: WISE-PaaS/AFS
Author-email: ben2019.chuang@advantech.com.tw
License: Apache License 2.0
Keywords: AFS,WISE-PaaS,AI framework service,ADVANTECH
Platform: UNKNOWN
License-File: LICENSE
Requires-Dist: requests
Requires-Dist: urllib3
Requires-Dist: boto3 (<=1.17)
Requires-Dist: botocore (<1.21.0,>=1.20.0)
Requires-Dist: pycrypto
